[
  {
    "id": "b1f12f91-e6aa-4b57-9316-668cda5bd785",
    "name": "Nuovo Mondo 2",
    "description": null,
    "stageNumber": 2,
    "color": "blue",
    "icon": "🌍",
    "status": "DRAFT",
    "isActive": true,
    "createdAt": "2026-05-04T13:05:11.774Z",
    "updatedAt": "2026-05-04T13:05:11.774Z",
    "levels": [
      {
        "id": "72666736-173b-40a4-8fc3-f8a64d8da1d2",
        "levelNumber": 4,
        "movesLimit": 20,
        "status": "DRAFT",
        "objective": {
          "type": "JELLY",
          "required": 5,
          "targetColor": "RED"
        },
        "grid": [
          ["YELLOW", "ICE",    "ORANGE", "RED",    "EMPTY"],
          ["ORANGE", "BLUE",   "YELLOW", "YELLOW", "ORANGE"],
          ["ORANGE", "EMPTY",  "RED",    "YELLOW", "EMPTY"],
          ["EMPTY",  "BLUE",   "BLUE",   "RED",    "ORANGE"],
          ["RED",    "WAFFLE", "ICE",    "YELLOW", "ICE"]
        ],
        "availablePieces": [
          { "type": "RED" },
          { "type": "BLUE", "point": 200 }
        ],
        "worldId": "b1f12f91-e6aa-4b57-9316-668cda5bd785",
        "createdAt": "2026-05-04T13:05:11.786Z",
        "updatedAt": "2026-05-04T13:05:11.786Z"
      },
      {
        "id": "208c4530-ff0c-4417-84cd-32af0b7f9e24",
        "levelNumber": 5,
        "movesLimit": 20,
        "status": "DRAFT",
        "objective": {
          "type": "JELLY",
          "required": 8,
          "targetColor": "BLUE"
        },
        "grid": [
          ["GREEN",  "WAFFLE", "BLUE",   "RED",    "ICE"],
          ["YELLOW", "GREEN",  "ICE",    "RED",    "ICE"],
          ["ORANGE", "BLUE",   "YELLOW", "YELLOW", "GREEN"],
          ["ORANGE", "YELLOW", "GREEN",  "YELLOW", "EMPTY"],
          ["BLUE",   "EMPTY",  "YELLOW", "BLUE",   "BLUE"]
        ],
        "availablePieces": [
          { "type": "RED" },
          { "type": "BLUE", "point": 200 }
        ],
        "worldId": "b1f12f91-e6aa-4b57-9316-668cda5bd785",
        "createdAt": "2026-05-04T13:05:11.793Z",
        "updatedAt": "2026-05-04T13:05:11.793Z"
      }
    ]
  },
  {
    "id": "cc2f19e7-c870-4c8e-a947-75e21156f812",
    "name": "Nuovo Mondo 1",
    "description": null,
    "stageNumber": 1,
    "color": "red",
    "icon": "🌍",
    "status": "DRAFT",
    "isActive": true,
    "createdAt": "2026-05-04T13:04:00.501Z",
    "updatedAt": "2026-05-04T13:05:35.036Z",
    "levels": [
      {
        "id": "2ef723d9-9e28-49ea-b759-6782fae0f8f2",
        "levelNumber": 1,
        "movesLimit": 15,
        "status": "DRAFT",
        "objective": {
          "type": "JELLY",
          "required": 9,
          "targetColor": "RED"
        },
        "grid": [
          ["EMPTY",  "EMPTY",   "RED",    "GREEN",   "BLUE"],
          ["EMPTY",  "BLUE",    "BLUE",   "BLUE",    "RED"],
          ["YELLOW", "GREEN",   "BLUE",   "EMPTY",   "YELLOW"],
          ["EMPTY",  "ORANGE",  "EMPTY",  "LICORICE","EMPTY"],
          ["EMPTY",  "EMPTY",   "GREEN",  "ORANGE",  "EMPTY"]
        ],
        "availablePieces": [
          { "type": "RED" },
          { "type": "BLUE",  "point": 200 },
          { "type": "GREEN", "point": 500 }
        ],
        "worldId": "cc2f19e7-c870-4c8e-a947-75e21156f812",
        "createdAt": "2026-05-04T13:04:20.331Z",
        "updatedAt": "2026-05-04T13:05:11.749Z"
      },
      {
        "id": "8f1f30c2-4cb1-45fe-abc9-cbc6fb99403c",
        "levelNumber": 2,
        "movesLimit": 25,
        "status": "DRAFT",
        "objective": {
          "type": "JELLY",
          "required": 9,
          "targetColor": "RED"
        },
        "grid": [
          ["EMPTY", "WAFFLE", "BLUE",  "BLUE",  "RED"],
          ["BLUE",  "RED",    "GREEN", "RED",   "GREEN"],
          ["BLUE",  "ICE",    "RED",   "EMPTY", "GREEN"],
          ["BLUE",  "EMPTY",  "EMPTY", "BLUE",  "EMPTY"],
          ["RED",   "GREEN",  "EMPTY", "EMPTY", "RED"]
        ],
        "availablePieces": [
          { "type": "RED" }
        ],
        "worldId": "cc2f19e7-c870-4c8e-a947-75e21156f812",
        "createdAt": "2026-05-04T13:04:20.337Z",
        "updatedAt": "2026-05-04T13:05:11.758Z"
      },
      {
        "id": "d729c91f-09dd-470f-9f2a-09a8461ffa93",
        "levelNumber": 3,
        "movesLimit": 25,
        "status": "DRAFT",
        "objective": {
          "type": "JELLY",
          "required": 6,
          "targetColor": "BLUE"
        },
        "grid": [
          ["EMPTY", "ICE",    "RED",   "GREEN", "RED"],
          ["RED",   "RED",    "RED",   "RED",   "RED"],
          ["BLUE",  "WAFFLE", "BLUE",  "ICE",   "BLUE"],
          ["ICE",   "RED",    "BLUE",  "GREEN", "RED"],
          ["EMPTY", "WAFFLE", "GREEN", "GREEN", "BLUE"]
        ],
        "availablePieces": [
          { "type": "RED" }
        ],
        "worldId": "cc2f19e7-c870-4c8e-a947-75e21156f812",
        "createdAt": "2026-05-04T13:04:03.346Z",
        "updatedAt": "2026-05-04T13:05:11.768Z"
      }
    ]
  }
]
